setup.py
distributions_mde1177/Binomialdistribution.py
distributions_mde1177/Gaussiandistribution.py
distributions_mde1177/Generaldistribution.py
distributions_mde1177/__init__.py
distributions_mde1177.egg-info/PKG-INFO
distributions_mde1177.egg-info/SOURCES.txt
distributions_mde1177.egg-info/dependency_links.txt
distributions_mde1177.egg-info/not-zip-safe
distributions_mde1177.egg-info/top_level.txt