Metadata-Version: 1.0
Name: distributions-mde1177
Version: 0.1
Summary: Gaussian distributions
Home-page: UNKNOWN
Author: Martin D. Edson
Author-email: m.edson373@gmail.com
License: UNKNOWN
Platform: UNKNOWN
